agently/__init__.py
agently/_default_init.py
agently/_default_settings.yaml
agently/base.py
agently/builtins/agent_extensions/AutoFuncExtension.py
agently/builtins/agent_extensions/ChatSessionExtension.py
agently/builtins/agent_extensions/ConfigurePromptExtension.py
agently/builtins/agent_extensions/KeyWaiterExtension.py
agently/builtins/agent_extensions/ToolExtension.py
agently/builtins/agent_extensions/__init__.py
agently/builtins/hookers/ConsoleHooker.py
agently/builtins/hookers/PureLoggerHooker.py
agently/builtins/hookers/SystemMessageHooker.py
agently/builtins/plugins/ModelRequester/OpenAICompatible.py
agently/builtins/plugins/PromptGenerator/AgentlyPromptGenerator.py
agently/builtins/plugins/ResponseParser/AgentlyResponseParser.py
agently/builtins/plugins/ToolManager/AgentlyToolManager.py
agently/builtins/plugins/__init__.py
agently/builtins/tools/Browse.py
agently/builtins/tools/Search.py
agently/builtins/tools/__init__.py
agently/core/Agent.py
agently/core/EventCenter.py
agently/core/ExtensionHandlers.py
agently/core/ModelRequest.py
agently/core/PluginManager.py
agently/core/Prompt.py
agently/core/Tool.py
agently/core/TriggerFlow/BluePrint.py
agently/core/TriggerFlow/Chunk.py
agently/core/TriggerFlow/Execution.py
agently/core/TriggerFlow/Process.py
agently/core/TriggerFlow/TriggerFlow.py
agently/core/TriggerFlow/__init__.py
agently/core/TriggerFlow/process/BaseProcess.py
agently/core/TriggerFlow/process/ForEachProcess.py
agently/core/TriggerFlow/process/MatchCaseProcess.py
agently/core/TriggerFlow/process/__init__.py
agently/core/__init__.py
agently/integrations/chromadb.py
agently/types/__init__.py
agently/types/data/__init__.py
agently/types/data/event.py
agently/types/data/prompt.py
agently/types/data/request.py
agently/types/data/response.py
agently/types/data/serializable.py
agently/types/data/tool.py
agently/types/plugins/EventHooker.py
agently/types/plugins/ModelRequester.py
agently/types/plugins/PromptGenerator.py
agently-4.0.7.1.dist-info/METADATA
agently-4.0.7.1.dist-info/WHEEL
agently-4.0.7.1.dist-info/licenses/LICENSE
agently-4.0.7.1.dist-info/RECORD
