Metadata-Version: 2.4
Name: agently
Version: 4.0.7.1
Summary: 
License: Apache-2.0
License-File: LICENSE
Author: Agently Team
Author-email: developer@agently.tech
Requires-Python: >=3.10
Classifier: License :: OSI Approved :: Apache Software License
Classifier: Programming Language :: Python :: 3
Classifier: Programming Language :: Python :: 3.10
Classifier: Programming Language :: Python :: 3.11
Classifier: Programming Language :: Python :: 3.12
Classifier: Programming Language :: Python :: 3.13
Classifier: Programming Language :: Python :: 3.14
Requires-Dist: greenlet (>=3.2.3,<4.0.0)
Requires-Dist: httpx (>=0.28.1,<0.29.0)
Requires-Dist: httpx-sse (>=0.4.1,<0.5.0)
Requires-Dist: json5 (>=0.12.0,<0.13.0)
Requires-Dist: packaging (>=25.0,<26.0)
Requires-Dist: pydantic (>=2.11.7,<3.0.0)
Requires-Dist: pyyaml (>=6.0.2,<7.0.0)
Requires-Dist: stamina (>=25.1.0,<26.0.0)
Requires-Dist: toml (>=0.10.2,<0.11.0)
